{"healthPoint":"55",
  "attackRange":"4",
  "attackPower":"7",
  "attackType":"hybrid",
  "mana":"null",
  "price":"8000",
  "name":"Rostam",
  "id":"110",
  "coolDown":"null",
  "type": "hero",
  "specialPower" : "Does not have special power",
  "target" : "null",
  "numOfTarget" : "null",
  "action" : "null",
  "buffs" : "null",
  "effectValue" : "null",
  "delay" : "null",
  "last" :"null",
  "friendOrEnemy" : "null",
  "locationOfTarget" : "null",
  "imagePath" : "view/Photos/Heros/Rostam/general_portrait_image_hex_f1@2x.png"
}