{"itemType":"collectible","locationOfTarget":"closest","last":"1","imagePath":"view\/Photos\/Items\/Nefrin Marg\/NefrinMarg.png","specification":"null","type":"item","friendOrEnemy":"friend\/enemy","target":"minion\/hero","delay":"null","price":"null","name":"Nefrin Marg","action":"addAction","numOfTarget":"1","id":"210","buffs":"healthPointWeaknessBuff","activationTime":"onDeath","effectValue":"8","user":"minion(random)","numInShop":"5","desc":"one random minion while dying can decrease one of the random nearest cards' health point"}